amulet_compiler_version.py
amulet_compiler_version-4.309027957683952396889703.17.dist-info/METADATA
amulet_compiler_version-4.309027957683952396889703.17.dist-info/WHEEL
amulet_compiler_version-4.309027957683952396889703.17.dist-info/top_level.txt
amulet_compiler_version-4.309027957683952396889703.17.dist-info/RECORD
