Metadata-Version: 2.4
Name: amulet-compiler-version
Version: 4.309027957683952396889703.17
Summary: A tiny library to allow dependencies to require the same compiler.
Author: James Clare
Project-URL: Homepage, https://www.amuletmc.com
Project-URL: Repository, https://github.com/Amulet-Team/Amulet-Compiler-Version
Project-URL: Issues, https://github.com/Amulet-Team/Amulet-Compiler-Version/issues
Classifier: Programming Language :: Python :: 3
Classifier: Operating System :: OS Independent
Requires-Python: >=3.9
Provides-Extra: dev
Requires-Dist: setuptools>=42; extra == "dev"
Requires-Dist: wheel; extra == "dev"
